kerstin/__init__.py
kerstin/mr2ct.py
kerstin-0.1.1.dist-info/METADATA
kerstin-0.1.1.dist-info/WHEEL
kerstin-0.1.1.dist-info/entry_points.txt
kerstin-0.1.1.dist-info/top_level.txt
kerstin-0.1.1.dist-info/RECORD
