Metadata-Version: 2.1
Name: kerstin
Version: 0.1.1
Summary: A very serious package about Dr. Kerstin Kläser.
Home-page: https://github.com/fepegar/kerstin
Author: Fernando Perez-Garcia
Author-email: fernando.perezgarcia.17@ucl.ac.uk
License: MIT license
Keywords: kerstin
Platform: UNKNOWN
Requires-Python: >=3.6
Requires-Dist: Pillow
Requires-Dist: gdown
